django_http2_push/__init__.py
django_http2_push/app.py
django_http2_push/middleware.py
django_http2_push/templatetags/__init__.py
django_http2_push/templatetags/static_push.py
django_http2_push-0.0b2.dist-info/METADATA
django_http2_push-0.0b2.dist-info/RECORD
django_http2_push-0.0b2.dist-info/WHEEL
django_http2_push-0.0b2.dist-info/top_level.txt
test/__init__.py
test/test_app.py
test/test_middleware.py
test/test_static_push.py
