Metadata-Version: 1.1
Name: django_http2_push
Version: 0.0b2
Summary: A simple way to add Header LINK
Home-page: https://github.com/ricardochaves/django_http2_push
Author: Ricardo Baltazar Chaves
Author-email: ricardobchaves6@gmail.com
License: MIT
Platform: UNKNOWN
Classifier: Programming Language :: Python
Classifier: Programming Language :: Python :: 3
Classifier: Programming Language :: Python :: 3.5
Classifier: Programming Language :: Python :: 3.7
Classifier: Framework :: Django :: 2.0
Classifier: Framework :: Django :: 2.1
Classifier: Environment :: Web Environment
Classifier: Natural Language :: Portuguese (Brazilian)
Classifier: Topic :: Internet :: WWW/HTTP :: WSGI :: Middleware
Classifier: Development Status :: 4 - Beta
Classifier: Framework :: Django
Classifier: Intended Audience :: Developers
Classifier: License :: OSI Approved :: MIT License
Classifier: Operating System :: OS Independent
